mlaide/__init__.py
mlaide/_api_client/__init__.py
mlaide/_api_client/api/__init__.py
mlaide/_api_client/api/_api_commons.py
mlaide/_api_client/api/artifact_api.py
mlaide/_api_client/api/experiment_api.py
mlaide/_api_client/api/run_api.py
mlaide/_api_client/client.py
mlaide/_api_client/dto/__init__.py
mlaide/_api_client/dto/artifact_dto.py
mlaide/_api_client/dto/artifact_ref_dto.py
mlaide/_api_client/dto/experiment_dto.py
mlaide/_api_client/dto/experiment_ref_dto.py
mlaide/_api_client/dto/git_dto.py
mlaide/_api_client/dto/helper.py
mlaide/_api_client/dto/run_dto.py
mlaide/_api_client/dto/runs_dto.py
mlaide/_api_client/dto/status_dto.py
mlaide/_api_client/errors.py
mlaide/_model_deser.py
mlaide/active_artifact.py
mlaide/active_run.py
mlaide/client.py
mlaide/error.py
mlaide/git_resolver.py
mlaide/mapper.py
mlaide/model/__init__.py
mlaide/model/artifact.py
mlaide/model/artifact_file.py
mlaide/model/artifact_ref.py
mlaide/model/git.py
mlaide/model/model.py
mlaide/model/run.py
mlaide/model/user_ref.py
mlaide-0.3.0.dist-info/LICENSE
mlaide-0.3.0.dist-info/WHEEL
mlaide-0.3.0.dist-info/METADATA
mlaide-0.3.0.dist-info/RECORD
