Metadata-Version: 2.1
Name: mlaide
Version: 0.3.0
Summary: 
Home-page: https://mlaide-ai.web.app/home
License: Apache-2.0
Author: Raman Singh
Author-email: mail.raman.s@gmail.com
Maintainer: Raman Singh
Maintainer-email: mail.raman.s@gmail.com
Requires-Python: >=3.8,<3.10
Classifier: License :: OSI Approved :: Apache Software License
Classifier: Programming Language :: Python :: 3
Classifier: Programming Language :: Python :: 3.8
Classifier: Programming Language :: Python :: 3.9
Requires-Dist: GitPython (>=3.1.24,<4.0.0)
Requires-Dist: cloudpickle (>=1.6.0,<2.0.0)
Requires-Dist: dataclasses-json (>=0.5.2,<0.6.0)
Requires-Dist: httpx (>=0.16.1,<0.17.0)
Requires-Dist: marshmallow (>=3.10.0,<4.0.0)
Requires-Dist: python-dateutil (>=2.8.1,<3.0.0)
Project-URL: Documentation, https://mlaide.github.io/docs/
Project-URL: Repository, https://github.com/MLAide/python-client
